chemspectranslator/__init__.py
chemspectranslator/data/translator_db.README
chemspectranslator/data/translator_db.csv
chemspectranslator/db.py
chemspectranslator/local_csv.py
chemspectranslator/source.py
chemspectranslator-1.1.0.dist-info/LICENSE
chemspectranslator-1.1.0.dist-info/WHEEL
chemspectranslator-1.1.0.dist-info/METADATA
chemspectranslator-1.1.0.dist-info/RECORD
